[
    {
        "path": "404.html",
        "type": "file",
        "md5": "d46ce33ee4eea08d20b86f94d089189f"
    },
    {
        "path": "anstossen",
        "type": "directory",
        "md5": false
    },
    {
        "path": "/anstossen/index.html",
        "type": "file",
        "md5": "76b83366877d408ae1703ea0afdd844b"
    },
    {
        "path": "assets",
        "type": "directory",
        "md5": false
    },
    {
        "path": "assets/css",
        "type": "directory",
        "md5": false
    },
    {
        "path": "/assets/css/editor.css",
        "type": "file",
        "md5": "8d94e2d8bb7f0673df5c4f26cd137a57"
    },
    {
        "path": "/assets/css/main.css",
        "type": "file",
        "md5": "1d23547907b4868910db55933ee8ff36"
    },
    {
        "path": "/assets/css/photoswipe.css",
        "type": "file",
        "md5": "151447f0cf3c9ef292a571bc74c9472c"
    },
    {
        "path": "/assets/css/style.css",
        "type": "file",
        "md5": "43dd81726fcb8935d9944eb78c35d86c"
    },
    {
        "path": "/assets/css/tiny-slider.css",
        "type": "file",
        "md5": "7b9c68dddade2be4260ce6e50d48f901"
    },
    {
        "path": "assets/js",
        "type": "directory",
        "md5": false
    },
    {
        "path": "/assets/js/photoswipe-ui-default.min.js",
        "type": "file",
        "md5": "d067f0883540b1ddda0e2c9ad1b14260"
    },
    {
        "path": "/assets/js/photoswipe.min.js",
        "type": "file",
        "md5": "017385b552f7e0d979e2e2fe6f324015"
    },
    {
        "path": "/assets/js/quicklink.umd.js",
        "type": "file",
        "md5": "61daff262ce6be0813e6b1b0341274d4"
    },
    {
        "path": "/assets/js/scripts.js",
        "type": "file",
        "md5": "29152ef6e92732b04ec00fcee4ecfe5b"
    },
    {
        "path": "/assets/js/scripts.min.js",
        "type": "file",
        "md5": "d79800375395a7ef07fbb24142e943e9"
    },
    {
        "path": "/assets/js/svg-fix.js",
        "type": "file",
        "md5": "7c0d2bb7276904b382e80bf2d85e8a96"
    },
    {
        "path": "/assets/js/svg-map.js",
        "type": "file",
        "md5": "9cb29ca1fd5b74d5be2977c9de4c1cb9"
    },
    {
        "path": "/assets/js/tiny-slider.min.js",
        "type": "file",
        "md5": "7a1b45e7b6165364b20e29f06742d32d"
    },
    {
        "path": "assets/svg",
        "type": "directory",
        "md5": false
    },
    {
        "path": "/assets/svg/gallery-icons-dark.svg",
        "type": "file",
        "md5": "0c70735af58190b563b2940b7a07007a"
    },
    {
        "path": "/assets/svg/gallery-icons-light.svg",
        "type": "file",
        "md5": "0bb1f41e2e459d23628833c37d8532f0"
    },
    {
        "path": "/assets/svg/svg-map.svg",
        "type": "file",
        "md5": "2ebaa7f276ff67ffcb9f587692e94cc2"
    },
    {
        "path": "autor",
        "type": "directory",
        "md5": false
    },
    {
        "path": "autor/clemens-richardt",
        "type": "directory",
        "md5": false
    },
    {
        "path": "/autor/clemens-richardt/index.html",
        "type": "file",
        "md5": "0815e6ca240962810565accba9c7ef18"
    },
    {
        "path": "autor/clemens-richardt/seite",
        "type": "directory",
        "md5": false
    },
    {
        "path": "autor/clemens-richardt/seite/2",
        "type": "directory",
        "md5": false
    },
    {
        "path": "/autor/clemens-richardt/seite/2/index.html",
        "type": "file",
        "md5": "9a09fac4e85b825e890e3d327450a9e8"
    },
    {
        "path": "autor/clemens-richardt/seite/3",
        "type": "directory",
        "md5": false
    },
    {
        "path": "/autor/clemens-richardt/seite/3/index.html",
        "type": "file",
        "md5": "323fd85156c0b277626100a7afedeedc"
    },
    {
        "path": "bankraub-for-good",
        "type": "directory",
        "md5": false
    },
    {
        "path": "/bankraub-for-good/index.html",
        "type": "file",
        "md5": "a2f4cbc26763185e8966a2c831c12b99"
    },
    {
        "path": "datenschutz",
        "type": "directory",
        "md5": false
    },
    {
        "path": "/datenschutz/index.html",
        "type": "file",
        "md5": "e79d4c86f0a8f43df961ead6e87324d7"
    },
    {
        "path": "der-zweck-entscheidet-die-mittel",
        "type": "directory",
        "md5": false
    },
    {
        "path": "/der-zweck-entscheidet-die-mittel/index.html",
        "type": "file",
        "md5": "cda213a24dc7cb1fe5170fd4f5591c9e"
    },
    {
        "path": "die-einfachen-dinge",
        "type": "directory",
        "md5": false
    },
    {
        "path": "/die-einfachen-dinge/index.html",
        "type": "file",
        "md5": "d3922eeadee8c466edaab648c5fa06c5"
    },
    {
        "path": "ethical-business",
        "type": "directory",
        "md5": false
    },
    {
        "path": "/ethical-business/index.html",
        "type": "file",
        "md5": "8c5c910d83788958798dcadc8833b8db"
    },
    {
        "path": "explore",
        "type": "directory",
        "md5": false
    },
    {
        "path": "/explore/index.html",
        "type": "file",
        "md5": "8491b431bcccb19d5d308fb9e359b223"
    },
    {
        "path": "feed.json",
        "type": "file",
        "md5": "e17b233cf543ba0ab112f5e7cb0ea698"
    },
    {
        "path": "feed.xml",
        "type": "file",
        "md5": "c9d46b401bd23099697753fff068321c"
    },
    {
        "path": "impressum",
        "type": "directory",
        "md5": false
    },
    {
        "path": "/impressum/index.html",
        "type": "file",
        "md5": "7d8a0d5a02d15b585571bcce7d952efd"
    },
    {
        "path": "index.html",
        "type": "file",
        "md5": "8374104cf77cf23288657555cc54e6cb"
    },
    {
        "path": "klimakompensation-der-moderne-ablassbrief",
        "type": "directory",
        "md5": false
    },
    {
        "path": "/klimakompensation-der-moderne-ablassbrief/index.html",
        "type": "file",
        "md5": "50fb803dafb95c802220b6052a4bd9ea"
    },
    {
        "path": "klimaschutz-fur-schwachkopfe-oder",
        "type": "directory",
        "md5": false
    },
    {
        "path": "/klimaschutz-fur-schwachkopfe-oder/index.html",
        "type": "file",
        "md5": "829900ae3c78abb76500b8041e19fd39"
    },
    {
        "path": "media",
        "type": "directory",
        "md5": false
    },
    {
        "path": "media/authors",
        "type": "directory",
        "md5": false
    },
    {
        "path": "media/authors/1",
        "type": "directory",
        "md5": false
    },
    {
        "path": "/media/authors/1/IMGP3839.jpg",
        "type": "file",
        "md5": "adcf13a33ec7c0a4851f74606b9303a3"
    },
    {
        "path": "/media/authors/1/IMGP5344.jpg",
        "type": "file",
        "md5": "8f6664fede6183629656a3d14ef1a20f"
    },
    {
        "path": "media/authors/1/responsive",
        "type": "directory",
        "md5": false
    },
    {
        "path": "/media/authors/1/responsive/IMGP3839-md.jpg",
        "type": "file",
        "md5": "602685328ba8329c18f765b93e4e5df6"
    },
    {
        "path": "/media/authors/1/responsive/IMGP3839-sm.jpg",
        "type": "file",
        "md5": "60cc93d57110b3a8fc940154fd1a8398"
    },
    {
        "path": "/media/authors/1/responsive/IMGP3839-xl.jpg",
        "type": "file",
        "md5": "0ef9123a28a78870542c221408e7e81b"
    },
    {
        "path": "/media/authors/1/responsive/IMGP3839-xs.jpg",
        "type": "file",
        "md5": "4807e32d65117b29f05775b19f66bab5"
    },
    {
        "path": "/media/authors/1/responsive/IMGP3839-xxl.jpg",
        "type": "file",
        "md5": "a82ff3409fd6ea7ef5cf6eac06225122"
    },
    {
        "path": "/media/authors/1/responsive/IMGP3839-xxxl.jpg",
        "type": "file",
        "md5": "cf9fc209af30cabf5d9d13197e2fefd6"
    },
    {
        "path": "/media/authors/1/responsive/IMGP5344-md.jpg",
        "type": "file",
        "md5": "e1c71dbd28bc29cd8a1db7ba48b98d1c"
    },
    {
        "path": "/media/authors/1/responsive/IMGP5344-sm.jpg",
        "type": "file",
        "md5": "146bd8fd26d35a7c6dd9fc07a95ea936"
    },
    {
        "path": "/media/authors/1/responsive/IMGP5344-xl.jpg",
        "type": "file",
        "md5": "652879b5e2506a61aa0cdb76aa8c11fc"
    },
    {
        "path": "/media/authors/1/responsive/IMGP5344-xs.jpg",
        "type": "file",
        "md5": "d3ebfb290db54f1502b0c4ff2bdf3639"
    },
    {
        "path": "/media/authors/1/responsive/IMGP5344-xxl.jpg",
        "type": "file",
        "md5": "f205749932473676e30133aa6faca2bb"
    },
    {
        "path": "/media/authors/1/responsive/IMGP5344-xxxl.jpg",
        "type": "file",
        "md5": "31b810956d6cedc9961ddca3a00e18af"
    },
    {
        "path": "media/posts",
        "type": "directory",
        "md5": false
    },
    {
        "path": "media/posts/11",
        "type": "directory",
        "md5": false
    },
    {
        "path": "/media/posts/11/IMGP0367.jpg",
        "type": "file",
        "md5": "e3ceddac4a7191104bcd3adc007e37a9"
    },
    {
        "path": "media/posts/11/responsive",
        "type": "directory",
        "md5": false
    },
    {
        "path": "/media/posts/11/responsive/IMGP0367-md.jpg",
        "type": "file",
        "md5": "b1a085ea48693f4d829b8be705a3b900"
    },
    {
        "path": "/media/posts/11/responsive/IMGP0367-sm.jpg",
        "type": "file",
        "md5": "b98c595f2c4b10f24b59b6be76e400d3"
    },
    {
        "path": "/media/posts/11/responsive/IMGP0367-xl.jpg",
        "type": "file",
        "md5": "0e24f946ee4a97dd7c2c136d3c26c222"
    },
    {
        "path": "/media/posts/11/responsive/IMGP0367-xs.jpg",
        "type": "file",
        "md5": "541ad5ad6d14cd41896dd0ddc7163562"
    },
    {
        "path": "/media/posts/11/responsive/IMGP0367-xxl.jpg",
        "type": "file",
        "md5": "e7e9530bd6b144dd500f4f14768d31f6"
    },
    {
        "path": "/media/posts/11/responsive/IMGP0367-xxxl.jpg",
        "type": "file",
        "md5": "0b46a445757ac171d9ca87aff1ed1333"
    },
    {
        "path": "media/posts/14",
        "type": "directory",
        "md5": false
    },
    {
        "path": "/media/posts/14/IMGP0702.jpg",
        "type": "file",
        "md5": "ec89f711f2e0faa948792a4c29ad7341"
    },
    {
        "path": "media/posts/14/responsive",
        "type": "directory",
        "md5": false
    },
    {
        "path": "/media/posts/14/responsive/IMGP0702-md.jpg",
        "type": "file",
        "md5": "3bcac9fc958dd4c1a0a9fae4f93e0509"
    },
    {
        "path": "/media/posts/14/responsive/IMGP0702-sm.jpg",
        "type": "file",
        "md5": "e4676635525bf2bb149019d2af5d7f30"
    },
    {
        "path": "/media/posts/14/responsive/IMGP0702-xl.jpg",
        "type": "file",
        "md5": "626014a30e78b9788f50495955cc10bf"
    },
    {
        "path": "/media/posts/14/responsive/IMGP0702-xs.jpg",
        "type": "file",
        "md5": "b6cded9817f63923e9c856cf3a0aadfe"
    },
    {
        "path": "/media/posts/14/responsive/IMGP0702-xxl.jpg",
        "type": "file",
        "md5": "a4852cd7fcccff7ad21693000f3a1bb7"
    },
    {
        "path": "/media/posts/14/responsive/IMGP0702-xxxl.jpg",
        "type": "file",
        "md5": "b39b80828ef4ed490c33631d865bb316"
    },
    {
        "path": "media/posts/17",
        "type": "directory",
        "md5": false
    },
    {
        "path": "/media/posts/17/IMGP0634.jpg",
        "type": "file",
        "md5": "2945e75632820ac160e143019aaeb151"
    },
    {
        "path": "media/posts/17/responsive",
        "type": "directory",
        "md5": false
    },
    {
        "path": "/media/posts/17/responsive/IMGP0634-md.jpg",
        "type": "file",
        "md5": "8bd8103c30720d0782e1b414e3f65b56"
    },
    {
        "path": "/media/posts/17/responsive/IMGP0634-sm.jpg",
        "type": "file",
        "md5": "577dd75d918e6e69a6b49d857bcd57e3"
    },
    {
        "path": "/media/posts/17/responsive/IMGP0634-xl.jpg",
        "type": "file",
        "md5": "4ff194fede8bcaab62518c89186ee349"
    },
    {
        "path": "/media/posts/17/responsive/IMGP0634-xs.jpg",
        "type": "file",
        "md5": "e41cb92077a1c6e11a58172b939efcdc"
    },
    {
        "path": "/media/posts/17/responsive/IMGP0634-xxl.jpg",
        "type": "file",
        "md5": "2572587b5e0b8c37cf19583957d14f6a"
    },
    {
        "path": "/media/posts/17/responsive/IMGP0634-xxxl.jpg",
        "type": "file",
        "md5": "508d0f96d4f3a315aa61836908ffe01c"
    },
    {
        "path": "media/posts/21",
        "type": "directory",
        "md5": false
    },
    {
        "path": "/media/posts/21/IMGP0646.jpg",
        "type": "file",
        "md5": "a98416d453cfe9a91d6e2b713ae112ac"
    },
    {
        "path": "/media/posts/21/IMGP1435.jpg",
        "type": "file",
        "md5": "4be809f02f66ec59ce9541a8622406ad"
    },
    {
        "path": "/media/posts/21/IMGP1439.jpg",
        "type": "file",
        "md5": "50b500d30d31f18ea4b9f700d79faf58"
    },
    {
        "path": "/media/posts/21/IMGP1445.jpg",
        "type": "file",
        "md5": "6a58a0440c8fd1fd60187eb64c646222"
    },
    {
        "path": "/media/posts/21/IMG_0114.jpg",
        "type": "file",
        "md5": "90bbf52b295c608189cb7186d7800659"
    },
    {
        "path": "media/posts/21/responsive",
        "type": "directory",
        "md5": false
    },
    {
        "path": "/media/posts/21/responsive/IMGP0646-md.jpg",
        "type": "file",
        "md5": "a18fe247a75367609923344635fd7ef1"
    },
    {
        "path": "/media/posts/21/responsive/IMGP0646-sm.jpg",
        "type": "file",
        "md5": "70444c279bb0fb948112d08138bbf2ba"
    },
    {
        "path": "/media/posts/21/responsive/IMGP0646-xl.jpg",
        "type": "file",
        "md5": "1d605c8a49e9975a3118175cf246f786"
    },
    {
        "path": "/media/posts/21/responsive/IMGP0646-xs.jpg",
        "type": "file",
        "md5": "da97ff7fabe02e916044f1b8eaf24f28"
    },
    {
        "path": "/media/posts/21/responsive/IMGP0646-xxl.jpg",
        "type": "file",
        "md5": "0443dfb7cac283db3ccb275b6f2caa01"
    },
    {
        "path": "/media/posts/21/responsive/IMGP0646-xxxl.jpg",
        "type": "file",
        "md5": "a589be55c6d488dfb2537e0a11a4bf0d"
    },
    {
        "path": "/media/posts/21/responsive/IMGP1435-md.jpg",
        "type": "file",
        "md5": "516beb7ce9b9b6d175bf8179e1289161"
    },
    {
        "path": "/media/posts/21/responsive/IMGP1435-sm.jpg",
        "type": "file",
        "md5": "4c09bd93134acd6eb078ec4e2888d9d8"
    },
    {
        "path": "/media/posts/21/responsive/IMGP1435-xl.jpg",
        "type": "file",
        "md5": "41d003b636c884cd2b9466957fa7df71"
    },
    {
        "path": "/media/posts/21/responsive/IMGP1435-xs.jpg",
        "type": "file",
        "md5": "fe1d23ec196c0e76328dc15fedd5e21c"
    },
    {
        "path": "/media/posts/21/responsive/IMGP1439-md.jpg",
        "type": "file",
        "md5": "c296af814dcf439be6f238ce46cc0225"
    },
    {
        "path": "/media/posts/21/responsive/IMGP1439-sm.jpg",
        "type": "file",
        "md5": "604e7d3b982fd9b3bd11590975199b77"
    },
    {
        "path": "/media/posts/21/responsive/IMGP1439-xl.jpg",
        "type": "file",
        "md5": "dc658640ebce6736fff8c09a00c9af99"
    },
    {
        "path": "/media/posts/21/responsive/IMGP1439-xs.jpg",
        "type": "file",
        "md5": "d06f02fe34a55c60e11c50117c73302d"
    },
    {
        "path": "/media/posts/21/responsive/IMGP1445-md.jpg",
        "type": "file",
        "md5": "c3ecf858b967f9c418b693471b1d3cdf"
    },
    {
        "path": "/media/posts/21/responsive/IMGP1445-sm.jpg",
        "type": "file",
        "md5": "a868243f28414b385cbd302d69e753b2"
    },
    {
        "path": "/media/posts/21/responsive/IMGP1445-xl.jpg",
        "type": "file",
        "md5": "b33aec94081df9aaaec90a160f3c8349"
    },
    {
        "path": "/media/posts/21/responsive/IMGP1445-xs.jpg",
        "type": "file",
        "md5": "bde1bf5e4633b3d6725cd6afcb979640"
    },
    {
        "path": "/media/posts/21/responsive/IMG_0114-md.jpg",
        "type": "file",
        "md5": "cc81e9ee5978c36c2155dd23423a4f13"
    },
    {
        "path": "/media/posts/21/responsive/IMG_0114-sm.jpg",
        "type": "file",
        "md5": "7ae0ebfdfde23bddc38dc4d8da355ba0"
    },
    {
        "path": "/media/posts/21/responsive/IMG_0114-xl.jpg",
        "type": "file",
        "md5": "7e2ae4e03e0f4b9265f7dc6223a019af"
    },
    {
        "path": "/media/posts/21/responsive/IMG_0114-xs.jpg",
        "type": "file",
        "md5": "3ab33d7abfd5e1866590a32ffc84c38a"
    },
    {
        "path": "media/posts/22",
        "type": "directory",
        "md5": false
    },
    {
        "path": "/media/posts/22/IMGP5024.jpg",
        "type": "file",
        "md5": "3ada68864648164eb2286a9df25b9033"
    },
    {
        "path": "media/posts/22/responsive",
        "type": "directory",
        "md5": false
    },
    {
        "path": "/media/posts/22/responsive/IMGP5024-md.jpg",
        "type": "file",
        "md5": "50ae68005beea27e92399cea0d536104"
    },
    {
        "path": "/media/posts/22/responsive/IMGP5024-sm.jpg",
        "type": "file",
        "md5": "e0ba7f2f281f0b6640ba9c71251a93d8"
    },
    {
        "path": "/media/posts/22/responsive/IMGP5024-xl.jpg",
        "type": "file",
        "md5": "2af638f126791d055d432787ffd2b05a"
    },
    {
        "path": "/media/posts/22/responsive/IMGP5024-xs.jpg",
        "type": "file",
        "md5": "ae4a4b4a5c2b685a1fe1607f092a209e"
    },
    {
        "path": "/media/posts/22/responsive/IMGP5024-xxl.jpg",
        "type": "file",
        "md5": "d35f00b22e69d56bb7037c7d3b9544cc"
    },
    {
        "path": "/media/posts/22/responsive/IMGP5024-xxxl.jpg",
        "type": "file",
        "md5": "a1e6ac7af52e2b72ea39ade0f8b8a82e"
    },
    {
        "path": "media/posts/24",
        "type": "directory",
        "md5": false
    },
    {
        "path": "/media/posts/24/IMGP1173.jpg",
        "type": "file",
        "md5": "50ca4b4d4d3743d24ab0ea55a14e7136"
    },
    {
        "path": "media/posts/24/responsive",
        "type": "directory",
        "md5": false
    },
    {
        "path": "/media/posts/24/responsive/IMGP1173-md.jpg",
        "type": "file",
        "md5": "4c7efaa281906c9a9d6bb56aab37653b"
    },
    {
        "path": "/media/posts/24/responsive/IMGP1173-sm.jpg",
        "type": "file",
        "md5": "f903717f2cda56681430a5fdb292effe"
    },
    {
        "path": "/media/posts/24/responsive/IMGP1173-xl.jpg",
        "type": "file",
        "md5": "b9f60613178c829ff28b393dc0f27dbe"
    },
    {
        "path": "/media/posts/24/responsive/IMGP1173-xs.jpg",
        "type": "file",
        "md5": "a6557ec5ed8d7296ac32501684476eb9"
    },
    {
        "path": "/media/posts/24/responsive/IMGP1173-xxl.jpg",
        "type": "file",
        "md5": "0b247c6db04eea1d6cdb39bb59ce3273"
    },
    {
        "path": "/media/posts/24/responsive/IMGP1173-xxxl.jpg",
        "type": "file",
        "md5": "0397dcb3dd96ef1ff22e459b09b2be85"
    },
    {
        "path": "/media/posts/24/responsive/Treibhausgase2005-md.jpg",
        "type": "file",
        "md5": "1c72a05cbec9cdd9279d9ee4986f0367"
    },
    {
        "path": "/media/posts/24/responsive/Treibhausgase2005-sm.jpg",
        "type": "file",
        "md5": "0c2f827c04cd1cb86f9ba7f1bfd1e511"
    },
    {
        "path": "/media/posts/24/responsive/Treibhausgase2005-xl.jpg",
        "type": "file",
        "md5": "1c72a05cbec9cdd9279d9ee4986f0367"
    },
    {
        "path": "/media/posts/24/responsive/Treibhausgase2005-xs.jpg",
        "type": "file",
        "md5": "6f37351f934a03ec86a517752b7d014f"
    },
    {
        "path": "/media/posts/24/Treibhausgase2005.jpg",
        "type": "file",
        "md5": "0d4399b8c2a3e5dd1831057a850286b9"
    },
    {
        "path": "media/posts/29",
        "type": "directory",
        "md5": false
    },
    {
        "path": "/media/posts/29/IMGP3128.jpg",
        "type": "file",
        "md5": "133c26626fe8fc22eaa5385629dc8854"
    },
    {
        "path": "media/posts/29/responsive",
        "type": "directory",
        "md5": false
    },
    {
        "path": "/media/posts/29/responsive/IMGP3128-md.jpg",
        "type": "file",
        "md5": "91879a962f7b38fc95040bdc1853b9c8"
    },
    {
        "path": "/media/posts/29/responsive/IMGP3128-sm.jpg",
        "type": "file",
        "md5": "3fc6d655ef0f64b39924688c3a95e39b"
    },
    {
        "path": "/media/posts/29/responsive/IMGP3128-xl.jpg",
        "type": "file",
        "md5": "c72a3e9062e63f502f243ff7e7bee0aa"
    },
    {
        "path": "/media/posts/29/responsive/IMGP3128-xs.jpg",
        "type": "file",
        "md5": "e038a98a58e9f4e05bfc31aa4cd8b7c2"
    },
    {
        "path": "/media/posts/29/responsive/IMGP3128-xxl.jpg",
        "type": "file",
        "md5": "edff242c259e63281bef75a2f7de1f19"
    },
    {
        "path": "/media/posts/29/responsive/IMGP3128-xxxl.jpg",
        "type": "file",
        "md5": "75332d0ed023fbfd447b2e025014591d"
    },
    {
        "path": "media/posts/30",
        "type": "directory",
        "md5": false
    },
    {
        "path": "media/posts/30/responsive",
        "type": "directory",
        "md5": false
    },
    {
        "path": "/media/posts/30/responsive/TomorrowBank-BankraubforGood-InstagramPosts2-1024x640-32-md.jpg",
        "type": "file",
        "md5": "1f4888164023edc5d0bd8b7f434c733a"
    },
    {
        "path": "/media/posts/30/responsive/TomorrowBank-BankraubforGood-InstagramPosts2-1024x640-32-sm.jpg",
        "type": "file",
        "md5": "42ab629a37ce9ba005e1e23cc456c2ef"
    },
    {
        "path": "/media/posts/30/responsive/TomorrowBank-BankraubforGood-InstagramPosts2-1024x640-32-xl.jpg",
        "type": "file",
        "md5": "a2320178ca08e7a3487d29a5edaaa6cc"
    },
    {
        "path": "/media/posts/30/responsive/TomorrowBank-BankraubforGood-InstagramPosts2-1024x640-32-xs.jpg",
        "type": "file",
        "md5": "84459babbecda0186671c7700a978158"
    },
    {
        "path": "/media/posts/30/responsive/TomorrowBank-BankraubforGood-InstagramPosts2-1024x640-32-xxl.jpg",
        "type": "file",
        "md5": "a2320178ca08e7a3487d29a5edaaa6cc"
    },
    {
        "path": "/media/posts/30/responsive/TomorrowBank-BankraubforGood-InstagramPosts2-1024x640-32-xxxl.jpg",
        "type": "file",
        "md5": "a2320178ca08e7a3487d29a5edaaa6cc"
    },
    {
        "path": "/media/posts/30/TomorrowBank-BankraubforGood-InstagramPosts2-1024x640-32.jpg",
        "type": "file",
        "md5": "7668270cbeb66bf3c9dca79fbf4e7f90"
    },
    {
        "path": "media/posts/31",
        "type": "directory",
        "md5": false
    },
    {
        "path": "media/posts/31/gallery",
        "type": "directory",
        "md5": false
    },
    {
        "path": "/media/posts/31/gallery/Sono-Motors-Sion-Powersharing-thumbnail.jpg",
        "type": "file",
        "md5": "52779dc90c8c138716ad5893b4055ec5"
    },
    {
        "path": "/media/posts/31/gallery/Sono-Motors-Sion-Powersharing.jpg",
        "type": "file",
        "md5": "4265cd490295f2f456e4fceb7db05d2a"
    },
    {
        "path": "media/posts/31/responsive",
        "type": "directory",
        "md5": false
    },
    {
        "path": "/media/posts/31/responsive/Sono-Motors-Sion-md.jpg",
        "type": "file",
        "md5": "5865faf1f46254f76faeeab6c01eeb92"
    },
    {
        "path": "/media/posts/31/responsive/Sono-Motors-Sion-Powersharing-md.jpg",
        "type": "file",
        "md5": "5c6298389dfda9e7d522fece5130700e"
    },
    {
        "path": "/media/posts/31/responsive/Sono-Motors-Sion-Powersharing-sm.jpg",
        "type": "file",
        "md5": "48ebc6c0af13ebb92e5d86fa21e6a80d"
    },
    {
        "path": "/media/posts/31/responsive/Sono-Motors-Sion-Powersharing-xl.jpg",
        "type": "file",
        "md5": "c7c3da16af43c63757126b7b16523218"
    },
    {
        "path": "/media/posts/31/responsive/Sono-Motors-Sion-Powersharing-xs.jpg",
        "type": "file",
        "md5": "8b52cbd1a17a6412d487e1b87132e6e9"
    },
    {
        "path": "/media/posts/31/responsive/Sono-Motors-Sion-sm.jpg",
        "type": "file",
        "md5": "f897fda90f38c0521f197606c0e89309"
    },
    {
        "path": "/media/posts/31/responsive/Sono-Motors-Sion-xl.jpg",
        "type": "file",
        "md5": "bc7a3d260af32128a53af62cc53b5ff1"
    },
    {
        "path": "/media/posts/31/responsive/Sono-Motors-Sion-xs.jpg",
        "type": "file",
        "md5": "3ad1390fd3f1fa210ac567a5341ad148"
    },
    {
        "path": "/media/posts/31/responsive/Sono-Motors-Sion-xxl.jpg",
        "type": "file",
        "md5": "59d0c4af8a7191805f18d66ca2ed70e6"
    },
    {
        "path": "/media/posts/31/responsive/Sono-Motors-Sion-xxxl.jpg",
        "type": "file",
        "md5": "3a3053edc2523d90e6a10f6b2c5d2d01"
    },
    {
        "path": "/media/posts/31/Sono-Motors-Sion-Powersharing.jpg",
        "type": "file",
        "md5": "4265cd490295f2f456e4fceb7db05d2a"
    },
    {
        "path": "/media/posts/31/Sono-Motors-Sion.jpg",
        "type": "file",
        "md5": "b372105f9b84ca33c3bf2659d7b781de"
    },
    {
        "path": "media/posts/33",
        "type": "directory",
        "md5": false
    },
    {
        "path": "/media/posts/33/IMGP3848.jpg",
        "type": "file",
        "md5": "30c4ca37347b362d2c00da953c5755c9"
    },
    {
        "path": "media/posts/33/responsive",
        "type": "directory",
        "md5": false
    },
    {
        "path": "/media/posts/33/responsive/IMGP3848-md.jpg",
        "type": "file",
        "md5": "ff9e0a358dcb83e711a7c9383b21c9e3"
    },
    {
        "path": "/media/posts/33/responsive/IMGP3848-sm.jpg",
        "type": "file",
        "md5": "dd48ece9c7eb4cdb3d14511b61a79b9e"
    },
    {
        "path": "/media/posts/33/responsive/IMGP3848-xl.jpg",
        "type": "file",
        "md5": "6fec7f1e859f6f90d680e7b8aecd4bc2"
    },
    {
        "path": "/media/posts/33/responsive/IMGP3848-xs.jpg",
        "type": "file",
        "md5": "343fca1c672eb200a611bc3f038728aa"
    },
    {
        "path": "/media/posts/33/responsive/IMGP3848-xxl.jpg",
        "type": "file",
        "md5": "be777e328a3e68f32ee0a0bdbe47f177"
    },
    {
        "path": "/media/posts/33/responsive/IMGP3848-xxxl.jpg",
        "type": "file",
        "md5": "aefd8fadc4d3735efa32186811f1f6f4"
    },
    {
        "path": "media/posts/34",
        "type": "directory",
        "md5": false
    },
    {
        "path": "/media/posts/34/IMG_3231-crichardt.com.jpg",
        "type": "file",
        "md5": "7a903dadaa414c27e275cd55978d91b7"
    },
    {
        "path": "media/posts/34/responsive",
        "type": "directory",
        "md5": false
    },
    {
        "path": "/media/posts/34/responsive/IMG_3231-crichardt.com-md.jpg",
        "type": "file",
        "md5": "60c543f1f74ab0e2734cd627713f79cd"
    },
    {
        "path": "/media/posts/34/responsive/IMG_3231-crichardt.com-sm.jpg",
        "type": "file",
        "md5": "4d4d222dcad2e9fa6e91b925636b7b64"
    },
    {
        "path": "/media/posts/34/responsive/IMG_3231-crichardt.com-xl.jpg",
        "type": "file",
        "md5": "24aa3f9d43c38fc4dbfe3a030023fdcd"
    },
    {
        "path": "/media/posts/34/responsive/IMG_3231-crichardt.com-xs.jpg",
        "type": "file",
        "md5": "3b4f6450bd90bc96e042e1927df7351d"
    },
    {
        "path": "/media/posts/34/responsive/IMG_3231-crichardt.com-xxl.jpg",
        "type": "file",
        "md5": "ec496cefa43992dba6a6b806b959c0e6"
    },
    {
        "path": "/media/posts/34/responsive/IMG_3231-crichardt.com-xxxl.jpg",
        "type": "file",
        "md5": "1895e6497e02ab324108bdf5d8a87825"
    },
    {
        "path": "media/posts/35",
        "type": "directory",
        "md5": false
    },
    {
        "path": "/media/posts/35/IMGP8174.jpg",
        "type": "file",
        "md5": "5b768ac7bb219cb11db73434f94bbdb3"
    },
    {
        "path": "media/posts/35/responsive",
        "type": "directory",
        "md5": false
    },
    {
        "path": "/media/posts/35/responsive/IMGP8174-md.jpg",
        "type": "file",
        "md5": "0a90422d3f37a020e2f1df9d9dff25f5"
    },
    {
        "path": "/media/posts/35/responsive/IMGP8174-sm.jpg",
        "type": "file",
        "md5": "67d063ad19db794e0ea5564f986f660b"
    },
    {
        "path": "/media/posts/35/responsive/IMGP8174-xl.jpg",
        "type": "file",
        "md5": "1524f7c2edf81981a745effbae71d17d"
    },
    {
        "path": "/media/posts/35/responsive/IMGP8174-xs.jpg",
        "type": "file",
        "md5": "cdbc27ed7523e56817fb26ac20aa8071"
    },
    {
        "path": "/media/posts/35/responsive/IMGP8174-xxl.jpg",
        "type": "file",
        "md5": "36e39e9bc2bd295571b31bb590b7be5c"
    },
    {
        "path": "/media/posts/35/responsive/IMGP8174-xxxl.jpg",
        "type": "file",
        "md5": "1d943a041ddd8f74006ce30041928216"
    },
    {
        "path": "media/posts/5",
        "type": "directory",
        "md5": false
    },
    {
        "path": "/media/posts/5/2_abb_entw-eev-sektoren_2019-02-26.png",
        "type": "file",
        "md5": "4664b653bf9ce09ba8a3e4a052162c70"
    },
    {
        "path": "/media/posts/5/IMGP0356.jpg",
        "type": "file",
        "md5": "3ab1eb75097da3c2a79bba988ab35b11"
    },
    {
        "path": "/media/posts/5/IMG_0288.jpg",
        "type": "file",
        "md5": "50c9257b2de8c057ed81e337c21a9a8f"
    },
    {
        "path": "media/posts/5/responsive",
        "type": "directory",
        "md5": false
    },
    {
        "path": "/media/posts/5/responsive/2_abb_entw-eev-sektoren_2019-02-26-md.png",
        "type": "file",
        "md5": "ee276cc2b3e8c280299d6c97dbe2c636"
    },
    {
        "path": "/media/posts/5/responsive/2_abb_entw-eev-sektoren_2019-02-26-sm.png",
        "type": "file",
        "md5": "b9576793cb0c857f18eb91bfd248d5a1"
    },
    {
        "path": "/media/posts/5/responsive/2_abb_entw-eev-sektoren_2019-02-26-xl.png",
        "type": "file",
        "md5": "ecfc2b51c4a8f5c3209d460b3ae3a8c7"
    },
    {
        "path": "/media/posts/5/responsive/2_abb_entw-eev-sektoren_2019-02-26-xs.png",
        "type": "file",
        "md5": "713b8dfaf4a8778cc73bdbda9b313f0b"
    },
    {
        "path": "/media/posts/5/responsive/IMGP0356-md.jpg",
        "type": "file",
        "md5": "a24ffabfb8892c989efad5b124ee937f"
    },
    {
        "path": "/media/posts/5/responsive/IMGP0356-sm.jpg",
        "type": "file",
        "md5": "0ef303537dc2e3b219898c7a81a42587"
    },
    {
        "path": "/media/posts/5/responsive/IMGP0356-xl.jpg",
        "type": "file",
        "md5": "1f71cc610b01324f093f89610c1fa2e3"
    },
    {
        "path": "/media/posts/5/responsive/IMGP0356-xs.jpg",
        "type": "file",
        "md5": "2b64e50f47ef98463bc96d50758532f2"
    },
    {
        "path": "/media/posts/5/responsive/IMGP0356-xxl.jpg",
        "type": "file",
        "md5": "11f2bc6bc6891ec0502b7b74499d0d60"
    },
    {
        "path": "/media/posts/5/responsive/IMGP0356-xxxl.jpg",
        "type": "file",
        "md5": "f785a6fa8e92b5f34f941525ba499d88"
    },
    {
        "path": "/media/posts/5/responsive/IMG_0288-md.jpg",
        "type": "file",
        "md5": "f701953b582f92273e1cf817500a82a6"
    },
    {
        "path": "/media/posts/5/responsive/IMG_0288-sm.jpg",
        "type": "file",
        "md5": "754db668cf7b84d40638efa067a2dd70"
    },
    {
        "path": "/media/posts/5/responsive/IMG_0288-xl.jpg",
        "type": "file",
        "md5": "1f41b41cb91b19c0c04069225cbed417"
    },
    {
        "path": "/media/posts/5/responsive/IMG_0288-xs.jpg",
        "type": "file",
        "md5": "dc6dc67160d573ef8e39f72a8d18c5e0"
    },
    {
        "path": "media/posts/6",
        "type": "directory",
        "md5": false
    },
    {
        "path": "/media/posts/6/20190317_210007.jpg",
        "type": "file",
        "md5": "ad7faa5f56d8514085fe523409e2736d"
    },
    {
        "path": "media/posts/6/responsive",
        "type": "directory",
        "md5": false
    },
    {
        "path": "/media/posts/6/responsive/20190317_210007-md.jpg",
        "type": "file",
        "md5": "239df9c98a234871fc924bca898b5cb0"
    },
    {
        "path": "/media/posts/6/responsive/20190317_210007-sm.jpg",
        "type": "file",
        "md5": "cc62c7820a3a8dcf1818f77c3136dcd6"
    },
    {
        "path": "/media/posts/6/responsive/20190317_210007-xl.jpg",
        "type": "file",
        "md5": "bef17629eeb2b367c5218911f2d82c94"
    },
    {
        "path": "/media/posts/6/responsive/20190317_210007-xs.jpg",
        "type": "file",
        "md5": "0e4788fa02466fbf26ae43540f4f5cf4"
    },
    {
        "path": "/media/posts/6/responsive/20190317_210007-xxl.jpg",
        "type": "file",
        "md5": "824633c15a8d729eb45327aeb9a6fe55"
    },
    {
        "path": "/media/posts/6/responsive/20190317_210007-xxxl.jpg",
        "type": "file",
        "md5": "71b671584768c94b82b0aea48792bbc6"
    },
    {
        "path": "media/tags",
        "type": "directory",
        "md5": false
    },
    {
        "path": "media/tags/11",
        "type": "directory",
        "md5": false
    },
    {
        "path": "/media/tags/11/IMGP3139.jpg",
        "type": "file",
        "md5": "13927180072a27c69550788ecb586e50"
    },
    {
        "path": "media/tags/11/responsive",
        "type": "directory",
        "md5": false
    },
    {
        "path": "/media/tags/11/responsive/IMGP3139-md.jpg",
        "type": "file",
        "md5": "cfb78c174c9505eecdce80806c3d2e5d"
    },
    {
        "path": "/media/tags/11/responsive/IMGP3139-sm.jpg",
        "type": "file",
        "md5": "49fc17574a8c4ab432f32ee68d71b821"
    },
    {
        "path": "/media/tags/11/responsive/IMGP3139-xl.jpg",
        "type": "file",
        "md5": "318e7739ef1584df3a57e961f113048d"
    },
    {
        "path": "/media/tags/11/responsive/IMGP3139-xs.jpg",
        "type": "file",
        "md5": "392f3f0b4a878e772cfa84687e1d7357"
    },
    {
        "path": "/media/tags/11/responsive/IMGP3139-xxl.jpg",
        "type": "file",
        "md5": "8040256a82dc545a3fb53a305ceb6140"
    },
    {
        "path": "/media/tags/11/responsive/IMGP3139-xxxl.jpg",
        "type": "file",
        "md5": "62f2df38b3768e5daaefb59c7d48f6a7"
    },
    {
        "path": "media/website",
        "type": "directory",
        "md5": false
    },
    {
        "path": "/media/website/CR_light-klein-no-border.png",
        "type": "file",
        "md5": "7eda96cf56cd2a9f186b43816a6acb5c"
    },
    {
        "path": "/media/website/IMGP1150.jpg",
        "type": "file",
        "md5": "424684ae0eb711ba2032aaea66c8566d"
    },
    {
        "path": "/media/website/IMGP2992.jpg",
        "type": "file",
        "md5": "51bcc1902fc288b2bff4c3a930dde4cd"
    },
    {
        "path": "/media/website/logo.png",
        "type": "file",
        "md5": "1cd2087ed172f8ea1e653d60db4a8688"
    },
    {
        "path": "media/website/responsive",
        "type": "directory",
        "md5": false
    },
    {
        "path": "/media/website/responsive/CR_light-klein-no-border-md.png",
        "type": "file",
        "md5": "3116e9a95ec8dc8a5d07aabb2fff07bd"
    },
    {
        "path": "/media/website/responsive/CR_light-klein-no-border-sm.png",
        "type": "file",
        "md5": "3116e9a95ec8dc8a5d07aabb2fff07bd"
    },
    {
        "path": "/media/website/responsive/CR_light-klein-no-border-xl.png",
        "type": "file",
        "md5": "3116e9a95ec8dc8a5d07aabb2fff07bd"
    },
    {
        "path": "/media/website/responsive/CR_light-klein-no-border-xs.png",
        "type": "file",
        "md5": "79dbdee4ca49ae9e89e93b360d229948"
    },
    {
        "path": "/media/website/responsive/CR_light-klein-no-border-xxl.png",
        "type": "file",
        "md5": "3116e9a95ec8dc8a5d07aabb2fff07bd"
    },
    {
        "path": "/media/website/responsive/CR_light-klein-no-border-xxxl.png",
        "type": "file",
        "md5": "3116e9a95ec8dc8a5d07aabb2fff07bd"
    },
    {
        "path": "/media/website/responsive/IMGP1150-md.jpg",
        "type": "file",
        "md5": "08c8cc1a034a5b75fb13adb975200b09"
    },
    {
        "path": "/media/website/responsive/IMGP1150-sm.jpg",
        "type": "file",
        "md5": "6519d09ec7da4b53e48d65adfc203f20"
    },
    {
        "path": "/media/website/responsive/IMGP1150-xl.jpg",
        "type": "file",
        "md5": "abbd17670ea733647e5aed37e4dbd591"
    },
    {
        "path": "/media/website/responsive/IMGP1150-xs.jpg",
        "type": "file",
        "md5": "896db31491f5aa206e66b7abd619e35a"
    },
    {
        "path": "/media/website/responsive/IMGP1150-xxl.jpg",
        "type": "file",
        "md5": "8a08d91eb757bf1973ce298e456d50fa"
    },
    {
        "path": "/media/website/responsive/IMGP1150-xxxl.jpg",
        "type": "file",
        "md5": "0916ebcf2dc0fddfb502c5c4b4d03b80"
    },
    {
        "path": "/media/website/responsive/IMGP2992-md.jpg",
        "type": "file",
        "md5": "9a69db431b0dfdf56c23c7542b940dd1"
    },
    {
        "path": "/media/website/responsive/IMGP2992-sm.jpg",
        "type": "file",
        "md5": "5cae4b7f2ab5432bcb91b11bc2dd9499"
    },
    {
        "path": "/media/website/responsive/IMGP2992-xl.jpg",
        "type": "file",
        "md5": "75e214e29a414636eafb4845d1184715"
    },
    {
        "path": "/media/website/responsive/IMGP2992-xs.jpg",
        "type": "file",
        "md5": "0b769e36e96c82604fde03aa4880ea81"
    },
    {
        "path": "/media/website/responsive/IMGP2992-xxl.jpg",
        "type": "file",
        "md5": "747878c2cb99d29d1a219ff23228be66"
    },
    {
        "path": "/media/website/responsive/IMGP2992-xxxl.jpg",
        "type": "file",
        "md5": "89d531c1c08d397b2693ec1816a13ab7"
    },
    {
        "path": "/media/website/responsive/logo-md.png",
        "type": "file",
        "md5": "f8e3a494493a694da4fe0c6ff31509db"
    },
    {
        "path": "/media/website/responsive/logo-sm.png",
        "type": "file",
        "md5": "fad89bd78f4cc917fe555c388edd34af"
    },
    {
        "path": "/media/website/responsive/logo-xl.png",
        "type": "file",
        "md5": "fde8df83bca5b2943d95d6a82daa056a"
    },
    {
        "path": "/media/website/responsive/logo-xs.png",
        "type": "file",
        "md5": "d17ab3ef3cb124c9e70710ff2bb47b23"
    },
    {
        "path": "/media/website/responsive/logo-xxl.png",
        "type": "file",
        "md5": "fde8df83bca5b2943d95d6a82daa056a"
    },
    {
        "path": "/media/website/responsive/logo-xxxl.png",
        "type": "file",
        "md5": "fde8df83bca5b2943d95d6a82daa056a"
    },
    {
        "path": "mut-offenheit-und-wahrhaftigkeit",
        "type": "directory",
        "md5": false
    },
    {
        "path": "/mut-offenheit-und-wahrhaftigkeit/index.html",
        "type": "file",
        "md5": "c8d039b62389c88b29ea90aac88f028e"
    },
    {
        "path": "nimby",
        "type": "directory",
        "md5": false
    },
    {
        "path": "/nimby/index.html",
        "type": "file",
        "md5": "006dfc7c1b5801da784e2961ebdce10e"
    },
    {
        "path": "print-it-baby",
        "type": "directory",
        "md5": false
    },
    {
        "path": "/print-it-baby/index.html",
        "type": "file",
        "md5": "0876873b6502480e910726b54e17b5a1"
    },
    {
        "path": "profitabel",
        "type": "directory",
        "md5": false
    },
    {
        "path": "/profitabel/index.html",
        "type": "file",
        "md5": "2c51dcb29859a3ac99a042c76404d434"
    },
    {
        "path": "robots.txt",
        "type": "file",
        "md5": "8b88ac7fa55e8d202db969eacd51f44d"
    },
    {
        "path": "schau-in-die-vergangenheit-und-du-siehst-die-zukunft",
        "type": "directory",
        "md5": false
    },
    {
        "path": "/schau-in-die-vergangenheit-und-du-siehst-die-zukunft/index.html",
        "type": "file",
        "md5": "787ebedadfae8404ed34c546b0ac5916"
    },
    {
        "path": "search.html",
        "type": "file",
        "md5": "3781c0c8ea564bcbb9b4449b3ca0dc45"
    },
    {
        "path": "seite",
        "type": "directory",
        "md5": false
    },
    {
        "path": "seite/2",
        "type": "directory",
        "md5": false
    },
    {
        "path": "/seite/2/index.html",
        "type": "file",
        "md5": "defbfd7e141c858d6889a044a70c68a1"
    },
    {
        "path": "seite/3",
        "type": "directory",
        "md5": false
    },
    {
        "path": "/seite/3/index.html",
        "type": "file",
        "md5": "0502bba34e2328b9f3b2ed7693460d12"
    },
    {
        "path": "sitemap.xml",
        "type": "file",
        "md5": "5b2a41f4d86c2aad69e52cf87e408754"
    },
    {
        "path": "sitemap.xsl",
        "type": "file",
        "md5": "03c2f9a7fdcc46ff05c435907614a0b8"
    },
    {
        "path": "smartphones",
        "type": "directory",
        "md5": false
    },
    {
        "path": "/smartphones/index.html",
        "type": "file",
        "md5": "c1d6b6074d7233a5f0262ae67cd5ec79"
    },
    {
        "path": "tag",
        "type": "directory",
        "md5": false
    },
    {
        "path": "tag/basics",
        "type": "directory",
        "md5": false
    },
    {
        "path": "/tag/basics/index.html",
        "type": "file",
        "md5": "5e0abcab54a0d2543f1710fbafd5bec3"
    },
    {
        "path": "tag/dslr",
        "type": "directory",
        "md5": false
    },
    {
        "path": "/tag/dslr/index.html",
        "type": "file",
        "md5": "9027bc0b9a5ad6adb6c17b73725779dc"
    },
    {
        "path": "tag/ethical_business",
        "type": "directory",
        "md5": false
    },
    {
        "path": "/tag/ethical_business/index.html",
        "type": "file",
        "md5": "d5cbe2122dcd17e3c7f880b3fedf71ba"
    },
    {
        "path": "tag/ethical_business/seite",
        "type": "directory",
        "md5": false
    },
    {
        "path": "tag/ethical_business/seite/2",
        "type": "directory",
        "md5": false
    },
    {
        "path": "/tag/ethical_business/seite/2/index.html",
        "type": "file",
        "md5": "d7ff9e7218438752ffb6f7aad4e5e2c5"
    },
    {
        "path": "tag/fotografie",
        "type": "directory",
        "md5": false
    },
    {
        "path": "/tag/fotografie/index.html",
        "type": "file",
        "md5": "a7dca46a007b3694933b81936d37d294"
    },
    {
        "path": "/tag/index.html",
        "type": "file",
        "md5": "1d4812f1e604517495492e735b1bcba2"
    }
]